djangoLrnd/__init__.py
djangoLrnd/apps.py
djangoLrnd/middleware.py
djangoLrnd/models.py
djangoLrnd/urls.py
djangoLrnd/views.py
djangoLrnd/migrations/0001_initial.py
djangoLrnd/migrations/__init__.py
djangoLrnd/templates/djangoLrnd/validate.html
djangoLrnd-3.3.dist-info/METADATA
djangoLrnd-3.3.dist-info/WHEEL
djangoLrnd-3.3.dist-info/top_level.txt
djangoLrnd-3.3.dist-info/RECORD
